fwauto/__init__.py
fwauto/__main__.py
fwauto/ai_utils.py
fwauto/auth.py
fwauto/chat_logger.py
fwauto/claude_code_installer.py
fwauto/cli.py
fwauto/command_logger.py
fwauto/config.py
fwauto/deploy_operations.py
fwauto/graph.py
fwauto/input_helper.py
fwauto/langsmith_config.py
fwauto/logging_config.py
fwauto/platforms.py
fwauto/prompt_manager.py
fwauto/scenario.py
fwauto/slash_commands.py
fwauto/state.py
fwauto/template_manager.py
fwauto/user_config.py
fwauto/utils.py
fwauto/cli_commands/__init__.py
fwauto/cli_commands/init.py
fwauto/nodes/__init__.py
fwauto/nodes/ai_brain.py
fwauto/nodes/build.py
fwauto/nodes/chat.py
fwauto/nodes/deploy.py
fwauto/nodes/init.py
fwauto/nodes/log.py
fwauto/prompts/chat.md
fwauto/prompts/claude_code.md
fwauto/prompts/fix_build_errors.md
fwauto/prompts/implement_feature.md
fwauto/prompts/log.md
fwauto/prompts/rag_query.md
fwauto/scripts/check.py
fwauto/scripts/config.py
fwauto/scripts/format.py
fwauto/scripts/lint.py
fwauto/templates/sdk_am62x_linux/metadata.toml
fwauto/templates/sdk_am62x_linux/build/Makefile
fwauto/templates/sdk_am62x_linux/deploy/deploy.py
fwauto/templates/sdk_stm32_keil/metadata.toml
fwauto/templates/sdk_stm32_keil/build/Makefile
fwauto/templates/sdk_stm32_keil/build/build.ps1
fwauto/templates/sdk_stm32_keil/deploy/Makefile
fwauto/templates/sdk_stm32_keil/deploy/deploy.ps1
fwauto-0.6.0.dist-info/METADATA
fwauto-0.6.0.dist-info/WHEEL
fwauto-0.6.0.dist-info/entry_points.txt
fwauto-0.6.0.dist-info/licenses/LICENSE.TXT
fwauto-0.6.0.dist-info/RECORD
