Metadata-Version: 2.4
Name: fwauto
Version: 0.6.0
Summary: FWAuto - AI-powered firmware automation tool. Your firmware copilot.
Project-URL: Homepage, https://www.fwauto.ai
Author-email: Kent Chiu <kent.cwg@gmail.com>
Maintainer-email: Kent Chiu <kent.cwg@gmail.com>
License: MIT
License-File: LICENSE.TXT
Keywords: ai,embedded,firmware,stm32
Classifier: Development Status :: 4 - Beta
Classifier: Environment :: Console
Classifier: Intended Audience :: Developers
Classifier: License :: OSI Approved :: MIT License
Classifier: Operating System :: OS Independent
Classifier: Programming Language :: Python :: 3
Classifier: Programming Language :: Python :: 3.12
Classifier: Programming Language :: Python :: 3.13
Classifier: Topic :: Software Development :: Build Tools
Classifier: Topic :: Software Development :: Embedded Systems
Requires-Python: <3.14,>=3.12
Requires-Dist: claude-agent-sdk
Requires-Dist: jinja2>=3.0.0
Requires-Dist: langchain-anthropic>=1.0.0a1
Requires-Dist: langchain>=1.0.0a5
Requires-Dist: langgraph>=1.0.0a3
Requires-Dist: langsmith>=0.1.0
Requires-Dist: prompt-toolkit>=3.0.0
Requires-Dist: requests>=2.28.0
Requires-Dist: tomli-w>=1.0.0
Requires-Dist: tomli>=2.0.1; python_version < '3.11'
Requires-Dist: typer>=0.12.0
Provides-Extra: dev
Requires-Dist: pyright>=1.1.391; extra == 'dev'
Requires-Dist: pytest>=7.0.0; extra == 'dev'
Requires-Dist: ruff>=0.8.4; extra == 'dev'
